opennb.py
opennb-0.3.0.dist-info/METADATA
opennb-0.3.0.dist-info/WHEEL
opennb-0.3.0.dist-info/entry_points.txt
opennb-0.3.0.dist-info/licenses/LICENSE
opennb-0.3.0.dist-info/RECORD
