Metadata-Version: 2.4
Name: opennb
Version: 0.3.0
Summary: Open Jupyter notebooks from GitHub repositories or URLs directly in Jupyter.
Project-URL: Homepage, https://github.com/basnijholt/opennb
Author-email: Bas Nijholt <bas@nijho.lt>
License-File: LICENSE
Keywords: development,download,github,jupyter,notebook,utilities
Classifier: Development Status :: 4 - Beta
Classifier: Environment :: Console
Classifier: Framework :: Jupyter
Classifier: Framework :: Jupyter :: JupyterLab
Classifier: Intended Audience :: Developers
Classifier: Intended Audience :: Science/Research
Classifier: License :: OSI Approved :: MIT License
Classifier: Operating System :: OS Independent
Classifier: Programming Language :: Python
Classifier: Programming Language :: Python :: 3
Classifier: Programming Language :: Python :: 3.10
Classifier: Programming Language :: Python :: 3.11
Classifier: Programming Language :: Python :: 3.12
Classifier: Programming Language :: Python :: 3.13
Classifier: Topic :: Software Development :: Libraries :: Python Modules
Classifier: Topic :: Utilities
Requires-Python: >=3.10
Requires-Dist: jupytext>=1.16.6
Requires-Dist: notebook
Provides-Extra: test
Requires-Dist: coverage; extra == 'test'
Requires-Dist: pytest; extra == 'test'
Requires-Dist: pytest-cov; extra == 'test'
